rtl/waveform_engine.v
module waveform_engine #(
    parameter ADDR_WIDTH = 10, // 2^10 = 1024 samples
    parameter DATA_WIDTH = 14  // 14-bit DAC resolution
)(
    input wire clk,          // System Clock (50MHz now, 165MHz later)
    input wire reset_n,      // Active-low Reset
    
    // --- Loading Interface (Port A) ---
    // This is how we will eventually get data from Python
    input  wire                  load_we,      // Write Enable
    input  wire [ADDR_WIDTH-1:0] load_addr,    // Address to write (0-1023)
    input  wire [DATA_WIDTH-1:0] load_data,    // Data to write
    
    // --- Control Interface ---
    input  wire                  ctrl_run,     // 1 = Play, 0 = Pause/Reset
    input  wire [31:0]           cfg_divider,  // Clock cycles per sample (Sample Rate)
                                               // e.g. 50MHz / 50 = 1MHz Sample Rate
    
    // --- Output Interface (Port B) ---
    output reg  [DATA_WIDTH-1:0] dac_out       // The 14-bit signal going to pins
);

    // 1. Infer the RAM (1024 x 14-bit)
    // This syntax tells Quartus/ModelSim to create a memory block
    reg [DATA_WIDTH-1:0] ram_block [0:(1<<ADDR_WIDTH)-1];

    // Port A: The "Writer" (Python side)
    always @(posedge clk) begin
        if (load_we) begin
            ram_block[load_addr] <= load_data;
        end
    end

    // 2. Playback Logic
    reg [31:0]           div_counter;  // Counts clock cycles
    reg [ADDR_WIDTH-1:0] read_ptr;     // Points to current sample (0-1023)
    
    always @(posedge clk or negedge reset_n) begin
        if (!reset_n) begin
            div_counter <= 0;
            read_ptr    <= 0;
            dac_out     <= 0;
        end else if (ctrl_run) begin
            // --- Running Mode ---
            
            if (div_counter >= cfg_divider - 1) begin
                // Time to move to next sample!
                div_counter <= 0;
                
                // Increment pointer and wrap around (Modulo math)
                read_ptr <= read_ptr + 1'b1; 
                
                // Fetch new data from RAM to Output
                // (This is a Synchronous Read)
                dac_out <= ram_block[read_ptr];
                
            end else begin
                // Not time yet, keep counting
                div_counter <= div_counter + 1;
            end
            
        end else begin
            // --- Stopped Mode ---
            div_counter <= 0;
            read_ptr    <= 0;
            // Optional: Keep holding the last value, or reset to 0?
            // Usually safest to reset DAC to 0 or mid-scale.
            dac_out     <= 0; 
        end
    end

endmodule

sim/waveform_engine_tb.v
`timescale 1ns / 1ps

module waveform_engine_tb;

    // 1. Declare signals to connect to the module
    // "reg" for things WE control (inputs to the chip)
    // "wire" for things the CHIP controls (outputs)
    reg clk;
    reg reset_n;
    reg load_we;
    reg [9:0] load_addr;
    reg [13:0] load_data;
    reg ctrl_run;
    reg [31:0] cfg_divider;
    
    wire [13:0] dac_out;

    // 2. Instantiate the Unit Under Test (UUT)
    waveform_engine #(
        .ADDR_WIDTH(10),
        .DATA_WIDTH(14)
    ) uut (
        .clk(clk),
        .reset_n(reset_n),
        .load_we(load_we),
        .load_addr(load_addr),
        .load_data(load_data),
        .ctrl_run(ctrl_run),
        .cfg_divider(cfg_divider),
        .dac_out(dac_out)
    );

    // 3. Clock Generation (The Heartbeat)
    // Toggle clock every 10ns -> 20ns period = 50MHz
    initial clk = 0;
    always #10 clk = ~clk;

    integer i;

    // 4. The Test Procedure
    initial begin
        // Setup for Waveform Viewer (GTKWave)
        $dumpfile("waveform.vcd");
        $dumpvars(0, waveform_engine_tb);

        // --- Zero out all memory ---
        $display("Clearing Memory...");
        reset_n = 0;
        clk = 0;
        load_we = 1;
        load_data = 0;
        
        // Loop through all 1024 addresses and write '0'
        for (i = 0; i < 1024; i = i + 1) begin
            load_addr = i;
            @(negedge clk);
        end
        
        load_we = 0;

        // --- STEP A: Initialize ---
        $display("Initializing...");
        reset_n = 0;      // Hold reset
        load_we = 0;
        ctrl_run = 0;
        cfg_divider = 5;  // Run at 1/5th speed (simulates slow sample rate)
        #100;
        reset_n = 1;      // Release reset
        #20;

        // --- STEP B: Load "Fake" Waveform (Simulate Python) ---
        $display("Loading RAM...");
        
        // Sample 0: Value 100
        load_addr = 0; load_data = 14'd100; load_we = 1; #20; 
        
        // Sample 1: Value 500
        load_addr = 1; load_data = 14'd500; load_we = 1; #20;
        
        // Sample 2: Value 1000
        load_addr = 2; load_data = 14'd1000; load_we = 1; #20;
        
        // Sample 3: Value 0
        load_addr = 3; load_data = 14'd0;    load_we = 1; #20;
        load_addr = 4; load_data = 14'd77;    load_we = 1; #20;

        load_we = 0; // Stop writing
        #50;

        // --- STEP C: Start Playback ---
        $display("Starting Playback...");
        ctrl_run = 1;

        // Let it run for 500ns to see the counter wrap a few times
        #2000;

        // --- STEP D: Finish ---
        $display("Test Complete.");
        $finish;
    end

endmodule

waveform.vcd
$date
	Wed Jan 28 15:28:27 2026
$end
$version
	Icarus Verilog
$end
$timescale
	1ps
$end
$scope module waveform_engine_tb $end
$var wire 14 ! dac_out [13:0] $end
$var reg 32 " cfg_divider [31:0] $end
$var reg 1 # clk $end
$var reg 1 $ ctrl_run $end
$var reg 10 % load_addr [9:0] $end
$var reg 14 & load_data [13:0] $end
$var reg 1 ' load_we $end
$var reg 1 ( reset_n $end
$var integer 32 ) i [31:0] $end
$scope module uut $end
$var wire 32 * cfg_divider [31:0] $end
$var wire 1 # clk $end
$var wire 1 $ ctrl_run $end
$var wire 10 + load_addr [9:0] $end
$var wire 14 , load_data [13:0] $end
$var wire 1 ' load_we $end
$var wire 1 ( reset_n $end
$var parameter 32 - ADDR_WIDTH $end
$var parameter 32 . DATA_WIDTH $end
$var reg 14 / dac_out [13:0] $end
$var reg 32 0 div_counter [31:0] $end
$var reg 10 1 read_ptr [9:0] $end
$upscope $end
$upscope $end
$enddefinitions $end
$comment Show the parameter values. $end
$dumpall
b1110 .
b1010 -
$end
#0
$dumpvars
b0 1
b0 0
b0 /
b0 ,
b0 +
bx *
b0 )
0(
1'
b0 &
b0 %
x$
0#
bx "
b0 !
$end
#10000
1#
#20000
b1 %
b1 +
b1 )
0#
#30000
1#
#40000
b10 %
b10 +
b10 )
0#
#50000
1#
#60000
b11 %
b11 +
b11 )
0#
#70000
1#
#80000
b100 %
b100 +
b100 )
0#
#90000
1#
#100000
b101 %
b101 +
b101 )
0#
#110000
1#
#120000
b110 %
b110 +
b110 )
0#
#130000
1#
#140000
b111 %
b111 +
b111 )
0#
#150000
1#
#160000
b1000 %
b1000 +
b1000 )
0#
#170000
1#
#180000
b1001 %
b1001 +
b1001 )
0#
#190000
1#
#200000
b1010 %
b1010 +
b1010 )
0#
#210000
1#
#220000
b1011 %
b1011 +
b1011 )
0#
#230000
1#
#240000
b1100 %
b1100 +
b1100 )
0#
#250000
1#
#260000
b1101 %
b1101 +
b1101 )
0#
#270000
1#
#280000
b1110 %
b1110 +
b1110 )
0#
#290000
1#
#300000
b1111 %
b1111 +
b1111 )
0#
#310000
1#
#320000
b10000 %
b10000 +
b10000 )
0#
#330000
1#
#340000
b10001 %
b10001 +
b10001 )
0#
#350000
1#
#360000
b10010 %
b10010 +
b10010 )
0#
#370000
1#
#380000
b10011 %
b10011 +
b10011 )
0#
#390000
1#
#400000
b10100 %
b10100 +
b10100 )
0#
#410000
1#
#420000
b10101 %
b10101 +
b10101 )
0#
#430000
1#
#440000
b10110 %
b10110 +
b10110 )
0#
#450000
1#
#460000
b10111 %
b10111 +
b10111 )
0#
#470000
1#
#480000
b11000 %
b11000 +
b11000 )
0#
#490000
1#
#500000
b11001 %
b11001 +
b11001 )
0#
#510000
1#
#520000
b11010 %
b11010 +
b11010 )
0#
#530000
1#
#540000
b11011 %
b11011 +
b11011 )
0#
#550000
1#
#560000
b11100 %
b11100 +
b11100 )
0#
#570000
1#
#580000
b11101 %
b11101 +
b11101 )
0#
#590000
1#
#600000
b11110 %
b11110 +
b11110 )
0#
#610000
1#
#620000
b11111 %
b11111 +
b11111 )
0#
#630000
1#
#640000
b100000 %
b100000 +
b100000 )
0#
#650000
1#
#660000
b100001 %
b100001 +
b100001 )
0#
#670000
1#
#680000
b100010 %
b100010 +
b100010 )
0#
#690000
1#
#700000
b100011 %
b100011 +
b100011 )
0#
#710000
1#
#720000
b100100 %
b100100 +
b100100 )
0#
#730000
1#
#740000
b100101 %
b100101 +
b100101 )
0#
#750000
1#
#760000
b100110 %
b100110 +
b100110 )
0#
#770000
1#
#780000
b100111 %
b100111 +
b100111 )
0#
#790000
1#
#800000
b101000 %
b101000 +
b101000 )
0#
#810000
1#
#820000
b101001 %
b101001 +
b101001 )
0#
#830000
1#
#840000
b101010 %
b101010 +
b101010 )
0#
#850000
1#
#860000
b101011 %
b101011 +
b101011 )
0#
#870000
1#
#880000
b101100 %
b101100 +
b101100 )
0#
#890000
1#
#900000
b101101 %
b101101 +
b101101 )
0#
#910000
1#
#920000
b101110 %
b101110 +
b101110 )
0#
#930000
1#
#940000
b101111 %
b101111 +
b101111 )
0#
#950000
1#
#960000
b110000 %
b110000 +
b110000 )
0#
#970000
1#
#980000
b110001 %
b110001 +
b110001 )
0#
#990000
1#
#1000000
b110010 %
b110010 +
b110010 )
0#
#1010000
1#
#1020000
b110011 %
b110011 +
b110011 )
0#
#1030000
1#
#1040000
b110100 %
b110100 +
b110100 )
0#
#1050000
1#
#1060000
b110101 %
b110101 +
b110101 )
0#
#1070000
1#
#1080000
b110110 %
b110110 +
b110110 )
0#
#1090000
1#
#1100000
b110111 %
b110111 +
b110111 )
0#
#1110000
1#
#1120000
b111000 %
b111000 +
b111000 )
0#
#1130000
1#
#1140000
b111001 %
b111001 +
b111001 )
0#
#1150000
1#
#1160000
b111010 %
b111010 +
b111010 )
0#
#1170000
1#
#1180000
b111011 %
b111011 +
b111011 )
0#
#1190000
1#
#1200000
b111100 %
b111100 +
b111100 )
0#
#1210000
1#
#1220000
b111101 %
b111101 +
b111101 )
0#
#1230000
1#
#1240000
b111110 %
b111110 +
b111110 )
0#
#1250000
1#
#1260000
b111111 %
b111111 +
b111111 )
0#
#1270000
1#
#1280000
b1000000 %
b1000000 +
b1000000 )
0#
#1290000
1#
#1300000
b1000001 %
b1000001 +
b1000001 )
0#
#1310000
1#
#1320000
b1000010 %
b1000010 +
b1000010 )
0#
#1330000
1#
#1340000
b1000011 %
b1000011 +
b1000011 )
0#
#1350000
1#
#1360000
b1000100 %
b1000100 +
b1000100 )
0#
#1370000
1#
#1380000
b1000101 %
b1000101 +
b1000101 )
0#
#1390000
1#
#1400000
b1000110 %
b1000110 +
b1000110 )
0#
#1410000
1#
#1420000
b1000111 %
b1000111 +
b1000111 )
0#
#1430000
1#
#1440000
b1001000 %
b1001000 +
b1001000 )
0#
#1450000
1#
#1460000
b1001001 %
b1001001 +
b1001001 )
0#
#1470000
1#
#1480000
b1001010 %
b1001010 +
b1001010 )
0#
#1490000
1#
#1500000
b1001011 %
b1001011 +
b1001011 )
0#
#1510000
1#
#1520000
b1001100 %
b1001100 +
b1001100 )
0#
#1530000
1#
#1540000
b1001101 %
b1001101 +
b1001101 )
0#
#1550000
1#
#1560000
b1001110 %
b1001110 +
b1001110 )
0#
#1570000
1#
#1580000
b1001111 %
b1001111 +
b1001111 )
0#
#1590000
1#
#1600000
b1010000 %
b1010000 +
b1010000 )
0#
#1610000
1#
#1620000
b1010001 %
b1010001 +
b1010001 )
0#
#1630000
1#
#1640000
b1010010 %
b1010010 +
b1010010 )
0#
#1650000
1#
#1660000
b1010011 %
b1010011 +
b1010011 )
0#
#1670000
1#
#1680000
b1010100 %
b1010100 +
b1010100 )
0#
#1690000
1#
#1700000
b1010101 %
b1010101 +
b1010101 )
0#
#1710000
1#
#1720000
b1010110 %
b1010110 +
b1010110 )
0#
#1730000
1#
#1740000
b1010111 %
b1010111 +
b1010111 )
0#
#1750000
1#
#1760000
b1011000 %
b1011000 +
b1011000 )
0#
#1770000
1#
#1780000
b1011001 %
b1011001 +
b1011001 )
0#
#1790000
1#
#1800000
b1011010 %
b1011010 +
b1011010 )
0#
#1810000
1#
#1820000
b1011011 %
b1011011 +
b1011011 )
0#
#1830000
1#
#1840000
b1011100 %
b1011100 +
b1011100 )
0#
#1850000
1#
#1860000
b1011101 %
b1011101 +
b1011101 )
0#
#1870000
1#
#1880000
b1011110 %
b1011110 +
b1011110 )
0#
#1890000
1#
#1900000
b1011111 %
b1011111 +
b1011111 )
0#
#1910000
1#
#1920000
b1100000 %
b1100000 +
b1100000 )
0#
#1930000
1#
#1940000
b1100001 %
b1100001 +
b1100001 )
0#
#1950000
1#
#1960000
b1100010 %
b1100010 +
b1100010 )
0#
#1970000
1#
#1980000
b1100011 %
b1100011 +
b1100011 )
0#
#1990000
1#
#2000000
b1100100 %
b1100100 +
b1100100 )
0#
#2010000
1#
#2020000
b1100101 %
b1100101 +
b1100101 )
0#
#2030000
1#
#2040000
b1100110 %
b1100110 +
b1100110 )
0#
#2050000
1#
#2060000
b1100111 %
b1100111 +
b1100111 )
0#
#2070000
1#
#2080000
b1101000 %
b1101000 +
b1101000 )
0#
#2090000
1#
#2100000
b1101001 %
b1101001 +
b1101001 )
0#
#2110000
1#
#2120000
b1101010 %
b1101010 +
b1101010 )
0#
#2130000
1#
#2140000
b1101011 %
b1101011 +
b1101011 )
0#
#2150000
1#
#2160000
b1101100 %
b1101100 +
b1101100 )
0#
#2170000
1#
#2180000
b1101101 %
b1101101 +
b1101101 )
0#
#2190000
1#
#2200000
b1101110 %
b1101110 +
b1101110 )
0#
#2210000
1#
#2220000
b1101111 %
b1101111 +
b1101111 )
0#
#2230000
1#
#2240000
b1110000 %
b1110000 +
b1110000 )
0#
#2250000
1#
#2260000
b1110001 %
b1110001 +
b1110001 )
0#
#2270000
1#
#2280000
b1110010 %
b1110010 +
b1110010 )
0#
#2290000
1#
#2300000
b1110011 %
b1110011 +
b1110011 )
0#
#2310000
1#
#2320000
b1110100 %
b1110100 +
b1110100 )
0#
#2330000
1#
#2340000
b1110101 %
b1110101 +
b1110101 )
0#
#2350000
1#
#2360000
b1110110 %
b1110110 +
b1110110 )
0#
#2370000
1#
#2380000
b1110111 %
b1110111 +
b1110111 )
0#
#2390000
1#
#2400000
b1111000 %
b1111000 +
b1111000 )
0#
#2410000
1#
#2420000
b1111001 %
b1111001 +
b1111001 )
0#
#2430000
1#
#2440000
b1111010 %
b1111010 +
b1111010 )
0#
#2450000
1#
#2460000
b1111011 %
b1111011 +
b1111011 )
0#
#2470000
1#
#2480000
b1111100 %
b1111100 +
b1111100 )
0#
#2490000
1#
#2500000
b1111101 %
b1111101 +
b1111101 )
0#
#2510000
1#
#2520000
b1111110 %
b1111110 +
b1111110 )
0#
#2530000
1#
#2540000
b1111111 %
b1111111 +
b1111111 )
0#
#2550000
1#
#2560000
b10000000 %
b10000000 +
b10000000 )
0#
#2570000
1#
#2580000
b10000001 %
b10000001 +
b10000001 )
0#
#2590000
1#
#2600000
b10000010 %
b10000010 +
b10000010 )
0#
#2610000
1#
#2620000
b10000011 %
b10000011 +
b10000011 )
0#
#2630000
1#
#2640000
b10000100 %
b10000100 +
b10000100 )
0#
#2650000
1#
#2660000
b10000101 %
b10000101 +
b10000101 )
0#
#2670000
1#
#2680000
b10000110 %
b10000110 +
b10000110 )
0#
#2690000
1#
#2700000
b10000111 %
b10000111 +
b10000111 )
0#
#2710000
1#
#2720000
b10001000 %
b10001000 +
b10001000 )
0#
#2730000
1#
#2740000
b10001001 %
b10001001 +
b10001001 )
0#
#2750000
1#
#2760000
b10001010 %
b10001010 +
b10001010 )
0#
#2770000
1#
#2780000
b10001011 %
b10001011 +
b10001011 )
0#
#2790000
1#
#2800000
b10001100 %
b10001100 +
b10001100 )
0#
#2810000
1#
#2820000
b10001101 %
b10001101 +
b10001101 )
0#
#2830000
1#
#2840000
b10001110 %
b10001110 +
b10001110 )
0#
#2850000
1#
#2860000
b10001111 %
b10001111 +
b10001111 )
0#
#2870000
1#
#2880000
b10010000 %
b10010000 +
b10010000 )
0#
#2890000
1#
#2900000
b10010001 %
b10010001 +
b10010001 )
0#
#2910000
1#
#2920000
b10010010 %
b10010010 +
b10010010 )
0#
#2930000
1#
#2940000
b10010011 %
b10010011 +
b10010011 )
0#
#2950000
1#
#2960000
b10010100 %
b10010100 +
b10010100 )
0#
#2970000
1#
#2980000
b10010101 %
b10010101 +
b10010101 )
0#
#2990000
1#
#3000000
b10010110 %
b10010110 +
b10010110 )
0#
#3010000
1#
#3020000
b10010111 %
b10010111 +
b10010111 )
0#
#3030000
1#
#3040000
b10011000 %
b10011000 +
b10011000 )
0#
#3050000
1#
#3060000
b10011001 %
b10011001 +
b10011001 )
0#
#3070000
1#
#3080000
b10011010 %
b10011010 +
b10011010 )
0#
#3090000
1#
#3100000
b10011011 %
b10011011 +
b10011011 )
0#
#3110000
1#
#3120000
b10011100 %
b10011100 +
b10011100 )
0#
#3130000
1#
#3140000
b10011101 %
b10011101 +
b10011101 )
0#
#3150000
1#
#3160000
b10011110 %
b10011110 +
b10011110 )
0#
#3170000
1#
#3180000
b10011111 %
b10011111 +
b10011111 )
0#
#3190000
1#
#3200000
b10100000 %
b10100000 +
b10100000 )
0#
#3210000
1#
#3220000
b10100001 %
b10100001 +
b10100001 )
0#
#3230000
1#
#3240000
b10100010 %
b10100010 +
b10100010 )
0#
#3250000
1#
#3260000
b10100011 %
b10100011 +
b10100011 )
0#
#3270000
1#
#3280000
b10100100 %
b10100100 +
b10100100 )
0#
#3290000
1#
#3300000
b10100101 %
b10100101 +
b10100101 )
0#
#3310000
1#
#3320000
b10100110 %
b10100110 +
b10100110 )
0#
#3330000
1#
#3340000
b10100111 %
b10100111 +
b10100111 )
0#
#3350000
1#
#3360000
b10101000 %
b10101000 +
b10101000 )
0#
#3370000
1#
#3380000
b10101001 %
b10101001 +
b10101001 )
0#
#3390000
1#
#3400000
b10101010 %
b10101010 +
b10101010 )
0#
#3410000
1#
#3420000
b10101011 %
b10101011 +
b10101011 )
0#
#3430000
1#
#3440000
b10101100 %
b10101100 +
b10101100 )
0#
#3450000
1#
#3460000
b10101101 %
b10101101 +
b10101101 )
0#
#3470000
1#
#3480000
b10101110 %
b10101110 +
b10101110 )
0#
#3490000
1#
#3500000
b10101111 %
b10101111 +
b10101111 )
0#
#3510000
1#
#3520000
b10110000 %
b10110000 +
b10110000 )
0#
#3530000
1#
#3540000
b10110001 %
b10110001 +
b10110001 )
0#
#3550000
1#
#3560000
b10110010 %
b10110010 +
b10110010 )
0#
#3570000
1#
#3580000
b10110011 %
b10110011 +
b10110011 )
0#
#3590000
1#
#3600000
b10110100 %
b10110100 +
b10110100 )
0#
#3610000
1#
#3620000
b10110101 %
b10110101 +
b10110101 )
0#
#3630000
1#
#3640000
b10110110 %
b10110110 +
b10110110 )
0#
#3650000
1#
#3660000
b10110111 %
b10110111 +
b10110111 )
0#
#3670000
1#
#3680000
b10111000 %
b10111000 +
b10111000 )
0#
#3690000
1#
#3700000
b10111001 %
b10111001 +
b10111001 )
0#
#3710000
1#
#3720000
b10111010 %
b10111010 +
b10111010 )
0#
#3730000
1#
#3740000
b10111011 %
b10111011 +
b10111011 )
0#
#3750000
1#
#3760000
b10111100 %
b10111100 +
b10111100 )
0#
#3770000
1#
#3780000
b10111101 %
b10111101 +
b10111101 )
0#
#3790000
1#
#3800000
b10111110 %
b10111110 +
b10111110 )
0#
#3810000
1#
#3820000
b10111111 %
b10111111 +
b10111111 )
0#
#3830000
1#
#3840000
b11000000 %
b11000000 +
b11000000 )
0#
#3850000
1#
#3860000
b11000001 %
b11000001 +
b11000001 )
0#
#3870000
1#
#3880000
b11000010 %
b11000010 +
b11000010 )
0#
#3890000
1#
#3900000
b11000011 %
b11000011 +
b11000011 )
0#
#3910000
1#
#3920000
b11000100 %
b11000100 +
b11000100 )
0#
#3930000
1#
#3940000
b11000101 %
b11000101 +
b11000101 )
0#
#3950000
1#
#3960000
b11000110 %
b11000110 +
b11000110 )
0#
#3970000
1#
#3980000
b11000111 %
b11000111 +
b11000111 )
0#
#3990000
1#
#4000000
b11001000 %
b11001000 +
b11001000 )
0#
#4010000
1#
#4020000
b11001001 %
b11001001 +
b11001001 )
0#
#4030000
1#
#4040000
b11001010 %
b11001010 +
b11001010 )
0#
#4050000
1#
#4060000
b11001011 %
b11001011 +
b11001011 )
0#
#4070000
1#
#4080000
b11001100 %
b11001100 +
b11001100 )
0#
#4090000
1#
#4100000
b11001101 %
b11001101 +
b11001101 )
0#
#4110000
1#
#4120000
b11001110 %
b11001110 +
b11001110 )
0#
#4130000
1#
#4140000
b11001111 %
b11001111 +
b11001111 )
0#
#4150000
1#
#4160000
b11010000 %
b11010000 +
b11010000 )
0#
#4170000
1#
#4180000
b11010001 %
b11010001 +
b11010001 )
0#
#4190000
1#
#4200000
b11010010 %
b11010010 +
b11010010 )
0#
#4210000
1#
#4220000
b11010011 %
b11010011 +
b11010011 )
0#
#4230000
1#
#4240000
b11010100 %
b11010100 +
b11010100 )
0#
#4250000
1#
#4260000
b11010101 %
b11010101 +
b11010101 )
0#
#4270000
1#
#4280000
b11010110 %
b11010110 +
b11010110 )
0#
#4290000
1#
#4300000
b11010111 %
b11010111 +
b11010111 )
0#
#4310000
1#
#4320000
b11011000 %
b11011000 +
b11011000 )
0#
#4330000
1#
#4340000
b11011001 %
b11011001 +
b11011001 )
0#
#4350000
1#
#4360000
b11011010 %
b11011010 +
b11011010 )
0#
#4370000
1#
#4380000
b11011011 %
b11011011 +
b11011011 )
0#
#4390000
1#
#4400000
b11011100 %
b11011100 +
b11011100 )
0#
#4410000
1#
#4420000
b11011101 %
b11011101 +
b11011101 )
0#
#4430000
1#
#4440000
b11011110 %
b11011110 +
b11011110 )
0#
#4450000
1#
#4460000
b11011111 %
b11011111 +
b11011111 )
0#
#4470000
1#
#4480000
b11100000 %
b11100000 +
b11100000 )
0#
#4490000
1#
#4500000
b11100001 %
b11100001 +
b11100001 )
0#
#4510000
1#
#4520000
b11100010 %
b11100010 +
b11100010 )
0#
#4530000
1#
#4540000
b11100011 %
b11100011 +
b11100011 )
0#
#4550000
1#
#4560000
b11100100 %
b11100100 +
b11100100 )
0#
#4570000
1#
#4580000
b11100101 %
b11100101 +
b11100101 )
0#
#4590000
1#
#4600000
b11100110 %
b11100110 +
b11100110 )
0#
#4610000
1#
#4620000
b11100111 %
b11100111 +
b11100111 )
0#
#4630000
1#
#4640000
b11101000 %
b11101000 +
b11101000 )
0#
#4650000
1#
#4660000
b11101001 %
b11101001 +
b11101001 )
0#
#4670000
1#
#4680000
b11101010 %
b11101010 +
b11101010 )
0#
#4690000
1#
#4700000
b11101011 %
b11101011 +
b11101011 )
0#
#4710000
1#
#4720000
b11101100 %
b11101100 +
b11101100 )
0#
#4730000
1#
#4740000
b11101101 %
b11101101 +
b11101101 )
0#
#4750000
1#
#4760000
b11101110 %
b11101110 +
b11101110 )
0#
#4770000
1#
#4780000
b11101111 %
b11101111 +
b11101111 )
0#
#4790000
1#
#4800000
b11110000 %
b11110000 +
b11110000 )
0#
#4810000
1#
#4820000
b11110001 %
b11110001 +
b11110001 )
0#
#4830000
1#
#4840000
b11110010 %
b11110010 +
b11110010 )
0#
#4850000
1#
#4860000
b11110011 %
b11110011 +
b11110011 )
0#
#4870000
1#
#4880000
b11110100 %
b11110100 +
b11110100 )
0#
#4890000
1#
#4900000
b11110101 %
b11110101 +
b11110101 )
0#
#4910000
1#
#4920000
b11110110 %
b11110110 +
b11110110 )
0#
#4930000
1#
#4940000
b11110111 %
b11110111 +
b11110111 )
0#
#4950000
1#
#4960000
b11111000 %
b11111000 +
b11111000 )
0#
#4970000
1#
#4980000
b11111001 %
b11111001 +
b11111001 )
0#
#4990000
1#
#5000000
b11111010 %
b11111010 +
b11111010 )
0#
#5010000
1#
#5020000
b11111011 %
b11111011 +
b11111011 )
0#
#5030000
1#
#5040000
b11111100 %
b11111100 +
b11111100 )
0#
#5050000
1#
#5060000
b11111101 %
b11111101 +
b11111101 )
0#
#5070000
1#
#5080000
b11111110 %
b11111110 +
b11111110 )
0#
#5090000
1#
#5100000
b11111111 %
b11111111 +
b11111111 )
0#
#5110000
1#
#5120000
b100000000 %
b100000000 +
b100000000 )
0#
#5130000
1#
#5140000
b100000001 %
b100000001 +
b100000001 )
0#
#5150000
1#
#5160000
b100000010 %
b100000010 +
b100000010 )
0#
#5170000
1#
#5180000
b100000011 %
b100000011 +
b100000011 )
0#
#5190000
1#
#5200000
b100000100 %
b100000100 +
b100000100 )
0#
#5210000
1#
#5220000
b100000101 %
b100000101 +
b100000101 )
0#
#5230000
1#
#5240000
b100000110 %
b100000110 +
b100000110 )
0#
#5250000
1#
#5260000
b100000111 %
b100000111 +
b100000111 )
0#
#5270000
1#
#5280000
b100001000 %
b100001000 +
b100001000 )
0#
#5290000
1#
#5300000
b100001001 %
b100001001 +
b100001001 )
0#
#5310000
1#
#5320000
b100001010 %
b100001010 +
b100001010 )
0#
#5330000
1#
#5340000
b100001011 %
b100001011 +
b100001011 )
0#
#5350000
1#
#5360000
b100001100 %
b100001100 +
b100001100 )
0#
#5370000
1#
#5380000
b100001101 %
b100001101 +
b100001101 )
0#
#5390000
1#
#5400000
b100001110 %
b100001110 +
b100001110 )
0#
#5410000
1#
#5420000
b100001111 %
b100001111 +
b100001111 )
0#
#5430000
1#
#5440000
b100010000 %
b100010000 +
b100010000 )
0#
#5450000
1#
#5460000
b100010001 %
b100010001 +
b100010001 )
0#
#5470000
1#
#5480000
b100010010 %
b100010010 +
b100010010 )
0#
#5490000
1#
#5500000
b100010011 %
b100010011 +
b100010011 )
0#
#5510000
1#
#5520000
b100010100 %
b100010100 +
b100010100 )
0#
#5530000
1#
#5540000
b100010101 %
b100010101 +
b100010101 )
0#
#5550000
1#
#5560000
b100010110 %
b100010110 +
b100010110 )
0#
#5570000
1#
#5580000
b100010111 %
b100010111 +
b100010111 )
0#
#5590000
1#
#5600000
b100011000 %
b100011000 +
b100011000 )
0#
#5610000
1#
#5620000
b100011001 %
b100011001 +
b100011001 )
0#
#5630000
1#
#5640000
b100011010 %
b100011010 +
b100011010 )
0#
#5650000
1#
#5660000
b100011011 %
b100011011 +
b100011011 )
0#
#5670000
1#
#5680000
b100011100 %
b100011100 +
b100011100 )
0#
#5690000
1#
#5700000
b100011101 %
b100011101 +
b100011101 )
0#
#5710000
1#
#5720000
b100011110 %
b100011110 +
b100011110 )
0#
#5730000
1#
#5740000
b100011111 %
b100011111 +
b100011111 )
0#
#5750000
1#
#5760000
b100100000 %
b100100000 +
b100100000 )
0#
#5770000
1#
#5780000
b100100001 %
b100100001 +
b100100001 )
0#
#5790000
1#
#5800000
b100100010 %
b100100010 +
b100100010 )
0#
#5810000
1#
#5820000
b100100011 %
b100100011 +
b100100011 )
0#
#5830000
1#
#5840000
b100100100 %
b100100100 +
b100100100 )
0#
#5850000
1#
#5860000
b100100101 %
b100100101 +
b100100101 )
0#
#5870000
1#
#5880000
b100100110 %
b100100110 +
b100100110 )
0#
#5890000
1#
#5900000
b100100111 %
b100100111 +
b100100111 )
0#
#5910000
1#
#5920000
b100101000 %
b100101000 +
b100101000 )
0#
#5930000
1#
#5940000
b100101001 %
b100101001 +
b100101001 )
0#
#5950000
1#
#5960000
b100101010 %
b100101010 +
b100101010 )
0#
#5970000
1#
#5980000
b100101011 %
b100101011 +
b100101011 )
0#
#5990000
1#
#6000000
b100101100 %
b100101100 +
b100101100 )
0#
#6010000
1#
#6020000
b100101101 %
b100101101 +
b100101101 )
0#
#6030000
1#
#6040000
b100101110 %
b100101110 +
b100101110 )
0#
#6050000
1#
#6060000
b100101111 %
b100101111 +
b100101111 )
0#
#6070000
1#
#6080000
b100110000 %
b100110000 +
b100110000 )
0#
#6090000
1#
#6100000
b100110001 %
b100110001 +
b100110001 )
0#
#6110000
1#
#6120000
b100110010 %
b100110010 +
b100110010 )
0#
#6130000
1#
#6140000
b100110011 %
b100110011 +
b100110011 )
0#
#6150000
1#
#6160000
b100110100 %
b100110100 +
b100110100 )
0#
#6170000
1#
#6180000
b100110101 %
b100110101 +
b100110101 )
0#
#6190000
1#
#6200000
b100110110 %
b100110110 +
b100110110 )
0#
#6210000
1#
#6220000
b100110111 %
b100110111 +
b100110111 )
0#
#6230000
1#
#6240000
b100111000 %
b100111000 +
b100111000 )
0#
#6250000
1#
#6260000
b100111001 %
b100111001 +
b100111001 )
0#
#6270000
1#
#6280000
b100111010 %
b100111010 +
b100111010 )
0#
#6290000
1#
#6300000
b100111011 %
b100111011 +
b100111011 )
0#
#6310000
1#
#6320000
b100111100 %
b100111100 +
b100111100 )
0#
#6330000
1#
#6340000
b100111101 %
b100111101 +
b100111101 )
0#
#6350000
1#
#6360000
b100111110 %
b100111110 +
b100111110 )
0#
#6370000
1#
#6380000
b100111111 %
b100111111 +
b100111111 )
0#
#6390000
1#
#6400000
b101000000 %
b101000000 +
b101000000 )
0#
#6410000
1#
#6420000
b101000001 %
b101000001 +
b101000001 )
0#
#6430000
1#
#6440000
b101000010 %
b101000010 +
b101000010 )
0#
#6450000
1#
#6460000
b101000011 %
b101000011 +
b101000011 )
0#
#6470000
1#
#6480000
b101000100 %
b101000100 +
b101000100 )
0#
#6490000
1#
#6500000
b101000101 %
b101000101 +
b101000101 )
0#
#6510000
1#
#6520000
b101000110 %
b101000110 +
b101000110 )
0#
#6530000
1#
#6540000
b101000111 %
b101000111 +
b101000111 )
0#
#6550000
1#
#6560000
b101001000 %
b101001000 +
b101001000 )
0#
#6570000
1#
#6580000
b101001001 %
b101001001 +
b101001001 )
0#
#6590000
1#
#6600000
b101001010 %
b101001010 +
b101001010 )
0#
#6610000
1#
#6620000
b101001011 %
b101001011 +
b101001011 )
0#
#6630000
1#
#6640000
b101001100 %
b101001100 +
b101001100 )
0#
#6650000
1#
#6660000
b101001101 %
b101001101 +
b101001101 )
0#
#6670000
1#
#6680000
b101001110 %
b101001110 +
b101001110 )
0#
#6690000
1#
#6700000
b101001111 %
b101001111 +
b101001111 )
0#
#6710000
1#
