rtl/waveform_engine.v
module waveform_engine #(
    parameter ADDR_WIDTH = 10, // 2^10 = 1024 samples
    parameter DATA_WIDTH = 14  // 14-bit DAC resolution
)(
    input wire clk,          // System Clock (50MHz now, 165MHz later)
    input wire reset_n,      // Active-low Reset
    
    // --- Loading Interface (Port A) ---
    // This is how we will eventually get data from Python
    input  wire                  load_we,      // Write Enable
    input  wire [ADDR_WIDTH-1:0] load_addr,    // Address to write (0-1023)
    input  wire [DATA_WIDTH-1:0] load_data,    // Data to write
    
    // --- Control Interface ---
    input  wire                  ctrl_run,     // 1 = Play, 0 = Pause/Reset
    input  wire [31:0]           cfg_divider,  // Clock cycles per sample (Sample Rate)
                                               // e.g. 50MHz / 50 = 1MHz Sample Rate
    
    // --- Output Interface (Port B) ---
    output reg  [DATA_WIDTH-1:0] dac_out       // The 14-bit signal going to pins
);

    // 1. Infer the RAM (1024 x 14-bit)
    // This syntax tells Quartus/ModelSim to create a memory block
    reg [DATA_WIDTH-1:0] ram_block [0:(1<<ADDR_WIDTH)-1];

    // Port A: The "Writer" (Python side)
    always @(posedge clk) begin
        if (load_we) begin
            ram_block[load_addr] <= load_data;
        end
    end

    // 2. Playback Logic
    reg [31:0]           div_counter;  // Counts clock cycles
    reg [ADDR_WIDTH-1:0] read_ptr;     // Points to current sample (0-1023)
    
    always @(posedge clk or negedge reset_n) begin
        if (!reset_n) begin
            div_counter <= 0;
            read_ptr    <= 0;
            dac_out     <= 0;
        end else if (ctrl_run) begin
            // --- Running Mode ---
            
            if (div_counter >= cfg_divider - 1) begin
                // Time to move to next sample!
                div_counter <= 0;
                
                // Increment pointer and wrap around (Modulo math)
                read_ptr <= read_ptr + 1'b1; 
                
                // Fetch new data from RAM to Output
                // (This is a Synchronous Read)
                dac_out <= ram_block[read_ptr];
                
            end else begin
                // Not time yet, keep counting
                div_counter <= div_counter + 1;
            end
            
        end else begin
            // --- Stopped Mode ---
            div_counter <= 0;
            read_ptr    <= 0;
            // Optional: Keep holding the last value, or reset to 0?
            // Usually safest to reset DAC to 0 or mid-scale.
            dac_out     <= 0; 
        end
    end

endmodule

rtl/avalon_waveform_wrapper.v
module avalon_waveform_wrapper (
    input  wire        clk,
    input  wire        reset_n,
    
    // --- Avalon-MM Slave Interface (Connects to HPS) ---
    // The HPS sees this module as a chunk of memory.
    input  wire [10:0] avs_address,     // 11 bits (Range 0-2047)
    input  wire        avs_write,
    input  wire [31:0] avs_writedata,
    input  wire        avs_read,
    output reg  [31:0] avs_readdata,

    // --- Conduit Interface (Connects to DAC pins) ---
    // These signals leave the chip or go to other FPGA modules.
    output wire [13:0] conduit_dac_out
);

    // --- Internal Configuration Registers ---
    // These hold the settings "Run" and "Speed"
    reg [31:0] reg_divider;
    reg        reg_run;

    // --- Address Decoding ---
    // 0 - 1023  : RAM Access
    // 1024      : Control Register (Start/Stop)
    // 1025      : Divider Register (Speed)
    
    wire is_ram_access = (avs_address < 1024);
    wire is_cfg_access = (avs_address >= 1024);

    // --- Instantiate Unit 1 (The Engine) ---
    waveform_engine #(
        .ADDR_WIDTH(10),
        .DATA_WIDTH(14)
    ) engine_inst (
        .clk(clk),
        .reset_n(reset_n),
        
        // --- The Router Logic ---
        // Only trigger a RAM write if the address is in the 0-1023 range
        .load_we   (avs_write && is_ram_access), 
        .load_addr (avs_address[9:0]),           // Strip top bit, keep [9:0]
        .load_data (avs_writedata[13:0]),        // Take bottom 14 bits of data
        
        // Control Signals from our internal registers
        .ctrl_run    (reg_run),
        .cfg_divider (reg_divider),
        .dac_out     (conduit_dac_out)
    );

    // --- Write Logic (Processor -> FPGA) ---
    always @(posedge clk or negedge reset_n) begin
        if (!reset_n) begin
            reg_run     <= 0;
            reg_divider <= 50; // Default: Slow speed (1 MHz)
        end else if (avs_write && is_cfg_access) begin
            // We only care if the address is >= 1024
            case (avs_address)
                11'd1024: reg_run     <= avs_writedata[0]; // Bit 0 is Run/Stop
                11'd1025: reg_divider <= avs_writedata;    // Whole word is Divider
            endcase
        end
    end

    // --- Read Logic (FPGA -> Processor) ---
    // This allows Python to check "Is it running?" or "What is the divider?"
    always @(posedge clk) begin
        if (avs_read) begin
            if (is_cfg_access) begin
                case (avs_address)
                    11'd1024: avs_readdata <= {31'b0, reg_run};
                    11'd1025: avs_readdata <= reg_divider;
                    default:  avs_readdata <= 32'b0;
                endcase
            end else begin
                // Reading back RAM is optional. 
                // Return a debug value so we know the bus is working.
                avs_readdata <= 32'hDEADBEEF; 
            end
        end
    end

endmodule

sim/avalon_waveform_wrapper_tb.v
`timescale 1ns / 1ps

module avalon_waveform_wrapper_tb;

    // --- Signals ---
    reg clk;
    reg reset_n;

    // Avalon-MM Slave Interface Signals
    reg  [10:0] avs_address;
    reg         avs_write;
    reg  [31:0] avs_writedata;
    reg         avs_read;
    wire [31:0] avs_readdata;

    // Exported Conduit
    wire [13:0] dac_out;

    // --- UUT: Avalon Wrapper ---
    avalon_waveform_wrapper uut (
        .clk(clk),
        .reset_n(reset_n),
        .avs_address(avs_address),
        .avs_write(avs_write),
        .avs_writedata(avs_writedata),
        .avs_read(avs_read),
        .avs_readdata(avs_readdata),
        .conduit_dac_out(dac_out)
    );

    // --- Clock Generation (50MHz) ---
    initial clk = 0;
    always #10 clk = ~clk;

    // --- Avalon Write Task ---
    // This encapsulates the Avalon-MM write protocol: 
    // Address and Data must be stable while Write is asserted.
    task avalon_write;
        input [10:0] addr;
        input [31:0] data;
        begin
            @(negedge clk);
            avs_address   = addr;
            avs_writedata = data;
            avs_write     = 1;
            @(negedge clk);
            avs_write     = 0;
            avs_address   = 0;
            avs_writedata = 0;
        end
    endtask

    // --- Stimulus ---
    initial begin
        $dumpfile("wrapper_sim.vcd");
        $dumpvars(0, avalon_waveform_wrapper_tb);

        // Initialization
        reset_n = 0;
        avs_write = 0;
        avs_read = 0;
        #100;
        reset_n = 1;
        #20;

        // 1. Configure Engine via Register Map
        // Address 1025 = Divider
        avalon_write(11'd1025, 32'd2); 
        
        // 2. Load Waveform Data via Memory Map
        // Address 0-2 = RAM
        avalon_write(11'd0, 32'd4096); 
        avalon_write(11'd1, 32'd8192);
        avalon_write(11'd2, 32'd16383);
        
        // 3. Enable Engine
        // Address 1024 = Control (Bit 0 is Run)
        avalon_write(11'd1024, 32'd1);

        #1000;
        $finish;
    end

endmodule

wrapper_sim.vcd
$date
	Wed Jan 28 17:55:05 2026
$end
$version
	Icarus Verilog
$end
$timescale
	1ps
$end
$scope module avalon_waveform_wrapper_tb $end
$var wire 14 ! dac_out [13:0] $end
$var wire 32 " avs_readdata [31:0] $end
$var reg 11 # avs_address [10:0] $end
$var reg 1 $ avs_read $end
$var reg 1 % avs_write $end
$var reg 32 & avs_writedata [31:0] $end
$var reg 1 ' clk $end
$var reg 1 ( reset_n $end
$scope module uut $end
$var wire 11 ) avs_address [10:0] $end
$var wire 1 $ avs_read $end
$var wire 1 % avs_write $end
$var wire 32 * avs_writedata [31:0] $end
$var wire 1 ' clk $end
$var wire 1 ( reset_n $end
$var wire 1 + is_ram_access $end
$var wire 1 , is_cfg_access $end
$var wire 14 - conduit_dac_out [13:0] $end
$var reg 32 . avs_readdata [31:0] $end
$var reg 32 / reg_divider [31:0] $end
$var reg 1 0 reg_run $end
$scope module engine_inst $end
$var wire 32 1 cfg_divider [31:0] $end
$var wire 1 ' clk $end
$var wire 1 0 ctrl_run $end
$var wire 10 2 load_addr [9:0] $end
$var wire 14 3 load_data [13:0] $end
$var wire 1 4 load_we $end
$var wire 1 ( reset_n $end
$var parameter 32 5 ADDR_WIDTH $end
$var parameter 32 6 DATA_WIDTH $end
$var reg 14 7 dac_out [13:0] $end
$var reg 32 8 div_counter [31:0] $end
$var reg 10 9 read_ptr [9:0] $end
$upscope $end
$upscope $end
$scope task avalon_write $end
$var reg 11 : addr [10:0] $end
$var reg 32 ; data [31:0] $end
$upscope $end
$upscope $end
$enddefinitions $end
$comment Show the parameter values. $end
$dumpall
b1110 6
b1010 5
$end
#0
$dumpvars
bx ;
bx :
b0 9
b0 8
b0 7
04
bx 3
bx 2
b110010 1
00
b110010 /
bx .
b0 -
x,
x+
bx *
bx )
0(
0'
bx &
0%
0$
bx #
bx "
b0 !
$end
#10000
1'
#20000
0'
#30000
1'
#40000
0'
#50000
1'
#60000
0'
#70000
1'
#80000
0'
#90000
1'
#100000
0'
1(
#110000
1'
#120000
b10 3
b1 2
1%
b10 &
b10 *
0+
1,
b10000000001 #
b10000000001 )
0'
b10 ;
b10000000001 :
#130000
b10 /
b10 1
1'
#140000
b0 3
b0 2
b1000000000000 ;
b0 :
b0 &
b0 *
1+
0,
b0 #
b0 )
0%
0'
#150000
1'
#160000
14
b1000000000000 3
1%
b1000000000000 &
b1000000000000 *
0'
#170000
1'
#180000
b0 3
04
b10000000000000 ;
b1 :
b0 &
b0 *
0%
0'
#190000
1'
#200000
14
b10000000000000 3
b1 2
1%
b10000000000000 &
b10000000000000 *
b1 #
b1 )
0'
#210000
1'
#220000
b0 3
b0 2
04
b11111111111111 ;
b10 :
b0 &
b0 *
b0 #
b0 )
0%
0'
#230000
1'
#240000
14
b11111111111111 3
b10 2
1%
b11111111111111 &
b11111111111111 *
b10 #
b10 )
0'
#250000
1'
#260000
b0 3
b0 2
04
b1 ;
b10000000000 :
b0 &
b0 *
b0 #
b0 )
0%
0'
#270000
1'
#280000
b1 3
1%
b1 &
b1 *
0+
1,
b10000000000 #
b10000000000 )
0'
#290000
10
1'
#300000
b0 3
b0 &
b0 *
1+
0,
b0 #
b0 )
0%
0'
#310000
b1 8
1'
#320000
0'
#330000
b1000000000000 !
b1000000000000 -
b1000000000000 7
b1 9
b0 8
1'
#340000
0'
#350000
b1 8
1'
#360000
0'
#370000
b10000000000000 !
b10000000000000 -
b10000000000000 7
b10 9
b0 8
1'
#380000
0'
#390000
b1 8
1'
#400000
0'
#410000
b11111111111111 !
b11111111111111 -
b11111111111111 7
b11 9
b0 8
1'
#420000
0'
#430000
b1 8
1'
#440000
0'
#450000
bx !
bx -
bx 7
b100 9
b0 8
1'
#460000
0'
#470000
b1 8
1'
#480000
0'
#490000
b101 9
b0 8
1'
#500000
0'
#510000
b1 8
1'
#520000
0'
#530000
b110 9
b0 8
1'
#540000
0'
#550000
b1 8
1'
#560000
0'
#570000
b111 9
b0 8
1'
#580000
0'
#590000
b1 8
1'
#600000
0'
#610000
b1000 9
b0 8
1'
#620000
0'
#630000
b1 8
1'
#640000
0'
#650000
b1001 9
b0 8
1'
#660000
0'
#670000
b1 8
1'
#680000
0'
#690000
b1010 9
b0 8
1'
#700000
0'
#710000
b1 8
1'
#720000
0'
#730000
b1011 9
b0 8
1'
#740000
0'
#750000
b1 8
1'
#760000
0'
#770000
b1100 9
b0 8
1'
#780000
0'
#790000
b1 8
1'
#800000
0'
#810000
b1101 9
b0 8
1'
#820000
0'
#830000
b1 8
1'
#840000
0'
#850000
b1110 9
b0 8
1'
#860000
0'
#870000
b1 8
1'
#880000
0'
#890000
b1111 9
b0 8
1'
#900000
0'
#910000
b1 8
1'
#920000
0'
#930000
b10000 9
b0 8
1'
#940000
0'
#950000
b1 8
1'
#960000
0'
#970000
b10001 9
b0 8
1'
#980000
0'
#990000
b1 8
1'
#1000000
0'
#1010000
b10010 9
b0 8
1'
#1020000
0'
#1030000
b1 8
1'
#1040000
0'
#1050000
b10011 9
b0 8
1'
#1060000
0'
#1070000
b1 8
1'
#1080000
0'
#1090000
b10100 9
b0 8
1'
#1100000
0'
#1110000
b1 8
1'
#1120000
0'
#1130000
b10101 9
b0 8
1'
#1140000
0'
#1150000
b1 8
1'
#1160000
0'
#1170000
b10110 9
b0 8
1'
#1180000
0'
#1190000
b1 8
1'
#1200000
0'
#1210000
b10111 9
b0 8
1'
#1220000
0'
#1230000
b1 8
1'
#1240000
0'
#1250000
b11000 9
b0 8
1'
#1260000
0'
#1270000
b1 8
1'
#1280000
0'
#1290000
b11001 9
b0 8
1'
