rtl/pulse_sequencer_avalon.v
`timescale 1ns/1ps

module pulse_sequencer_avalon (
    input  wire        clk,
    input  wire        reset_n,

    // Avalon-MM Slave Interface
    input  wire [4:0]  avs_s0_address,
    input  wire        avs_s0_write,
    input  wire [31:0] avs_s0_writedata,
    input  wire        avs_s0_read,
    output reg  [31:0] avs_s0_readdata,

    // Physical Outputs
    output reg         aom_rp_out,
    output reg         aom_ro_out,
    output reg         sync_out       // Active-low; idles high
);

    // --- Register File ---
    reg [31:0] rp_start, rp_dur;
    reg [31:0] ro_start, ro_dur;
    reg [31:0] sync_start;
    reg [31:0] seq_limit;
    reg [31:0] repeat_limit;

    // --- Internal State ---
    reg        start_trigger;
    reg        stop_req;
    reg        running;
    reg [31:0] timer;
    reg [31:0] repeat_count;

    // Register map:
    //   0x00  Control / Status  (W: bit0=start, bit1=stop | R: bit0=running)
    //   0x01  seq_limit         Period length in clock cycles
    //   0x02  rp_start          RP AOM pulse start (cycles from period start)
    //   0x03  rp_dur            RP AOM pulse duration (cycles)
    //   0x04  ro_start          RO AOM pulse start
    //   0x05  ro_dur            RO AOM pulse duration
    //   0x06  sync_start        Sync pulse start (duration fixed at SYNC_DUR_FIXED)
    //   0x07  repeat_limit      0 = infinite; N = run N periods then stop
    //   0x08  repeat_count      R/O: number of period resets completed since start

    localparam SYNC_DUR_FIXED = 32'd20;

    // -------------------------------------------------------------------------
    // Avalon-MM Write Logic
    // -------------------------------------------------------------------------
    always @(posedge clk or negedge reset_n) begin
        if (!reset_n) begin
            rp_start      <= 0;
            rp_dur        <= 0;
            ro_start      <= 0;
            ro_dur        <= 0;
            sync_start    <= 0;
            seq_limit     <= 32'd5000;
            repeat_limit  <= 32'd1;
            start_trigger <= 0;
            stop_req      <= 0;
        end else begin
            // One-cycle strobes; auto-clear each cycle so the engine sees
            // exactly one pulse regardless of how long the host holds the write.
            start_trigger <= 0;
            stop_req      <= 0;

            if (avs_s0_write) begin
                case (avs_s0_address)
                    5'h00: begin
                        start_trigger <= avs_s0_writedata[0];
                        stop_req      <= avs_s0_writedata[1];
                    end
                    5'h01: seq_limit    <= avs_s0_writedata;
                    5'h02: rp_start     <= avs_s0_writedata;
                    5'h03: rp_dur       <= avs_s0_writedata;
                    5'h04: ro_start     <= avs_s0_writedata;
                    5'h05: ro_dur       <= avs_s0_writedata;
                    5'h06: sync_start   <= avs_s0_writedata;
                    5'h07: repeat_limit <= avs_s0_writedata;
                endcase
            end
        end
    end

    // -------------------------------------------------------------------------
    // Avalon-MM Read Logic  (read latency = 1 cycle)
    // -------------------------------------------------------------------------
    always @(posedge clk or negedge reset_n) begin
        if (!reset_n) begin
            avs_s0_readdata <= 32'd0;
        end else if (avs_s0_read) begin
            case (avs_s0_address)
                5'h00: avs_s0_readdata <= {31'd0, running};
                5'h01: avs_s0_readdata <= seq_limit;
                5'h02: avs_s0_readdata <= rp_start;
                5'h03: avs_s0_readdata <= rp_dur;
                5'h04: avs_s0_readdata <= ro_start;
                5'h05: avs_s0_readdata <= ro_dur;
                5'h06: avs_s0_readdata <= sync_start;
                5'h07: avs_s0_readdata <= repeat_limit;
                5'h08: avs_s0_readdata <= repeat_count;
                default: avs_s0_readdata <= 32'hDEADBEEF;
            endcase
        end
    end

    // -------------------------------------------------------------------------
    // Pulse Generation Engine
    // -------------------------------------------------------------------------
    always @(posedge clk or negedge reset_n) begin
        if (!reset_n) begin
            timer        <= 32'd0;
            repeat_count <= 32'd0;
            running      <= 1'b0;
            aom_rp_out   <= 1'b0;
            aom_ro_out   <= 1'b0;
            sync_out     <= 1'b1;
        end else begin

            // Start: only honoured when idle
            if (start_trigger && !running) begin
                running      <= 1'b1;
                timer        <= 32'd0;
                repeat_count <= 32'd0;
            end

            // Stop: immediate halt; takes priority over the running branch below
            if (stop_req && running) begin
                running    <= 1'b0;
                aom_rp_out <= 1'b0;
                aom_ro_out <= 1'b0;
                sync_out   <= 1'b1;
            end else if (running) begin
                timer <= timer + 1;

                // All comparisons use the current (pre-increment) value of timer,
                // so outputs are registered one cycle after the timer value that
                // qualified them -- this is a predictable, fixed one-cycle latency.
                aom_rp_out <= (timer >= rp_start) && (timer < (rp_start + rp_dur));
                aom_ro_out <= (timer >= ro_start) && (timer < (ro_start + ro_dur));
                sync_out   <= ~((timer >= sync_start) && (timer < (sync_start + SYNC_DUR_FIXED)));

                // End-of-period: using >= so a mid-run seq_limit reduction is
                // caught without waiting for the timer to wrap.
                // NOTE: seq_limit = 0 is illegal; minimum useful value is 1.
                if (timer >= seq_limit - 1) begin
                    if ((repeat_limit == 0) || (repeat_count + 1 < repeat_limit)) begin
                        // Loop: reset timer, count the completed period
                        timer        <= 32'd0;
                        repeat_count <= repeat_count + 1;
                    end else begin
                        // Done: deassert all outputs cleanly
                        running    <= 1'b0;
                        aom_rp_out <= 1'b0;
                        aom_ro_out <= 1'b0;
                        sync_out   <= 1'b1;
                    end
                end
            end

        end
    end

endmodule

sim/pulse_sequencer_avalon_tb.v
`timescale 1ns/1ps

module pulse_sequencer_avalon_tb;

    // -------------------------------------------------------------------------
    // DUT signals
    // -------------------------------------------------------------------------
    reg         clk;
    reg         reset_n;
    reg  [4:0]  avs_address;
    reg         avs_write;
    reg         avs_read;
    reg  [31:0] avs_writedata;
    wire [31:0] avs_readdata;
    wire        aom_rp_out, aom_ro_out, sync_out;

    // -------------------------------------------------------------------------
    // DUT instantiation
    // -------------------------------------------------------------------------
    pulse_sequencer_avalon uut (
        .clk              (clk),
        .reset_n          (reset_n),
        .avs_s0_address   (avs_address),
        .avs_s0_write     (avs_write),
        .avs_s0_writedata (avs_writedata),
        .avs_s0_read      (avs_read),
        .avs_s0_readdata  (avs_readdata),
        .aom_rp_out       (aom_rp_out),
        .aom_ro_out       (aom_ro_out),
        .sync_out         (sync_out)
    );

    // -------------------------------------------------------------------------
    // 50 MHz clock
    // -------------------------------------------------------------------------
    initial clk = 0;
    always #10 clk = ~clk;  // 20 ns period

    // -------------------------------------------------------------------------
    // Tasks
    //
    // Stimulus is driven on negedge so it meets setup time at the next posedge.
    // -------------------------------------------------------------------------

    // Write a register. Data is presented for exactly one clock cycle.
    task write_reg;
        input [4:0]  addr;
        input [31:0] data;
        begin
            @(negedge clk);
            avs_address   = addr;
            avs_writedata = data;
            avs_write     = 1;
            @(negedge clk);
            avs_write     = 0;
        end
    endtask

    // Read a register (latency = 1).  After the task returns, avs_readdata
    // holds the result and is stable until the next bus transaction.
    task read_reg;
        input [4:0] addr;
        begin
            @(negedge clk);
            avs_address = addr;
            avs_read    = 1;
            @(posedge clk);   // data is registered on this rising edge
            @(negedge clk);   // wait for output to settle, then deassert
            avs_read    = 0;
        end
    endtask

    // -------------------------------------------------------------------------
    // Pass/fail bookkeeping
    // -------------------------------------------------------------------------
    integer fail_count;

    task check;
        input [255:0] label;      // test name (up to 32 chars)
        input [31:0]  got;
        input [31:0]  expected;
        begin
            if (got !== expected) begin
                $display("FAIL  %-20s  got=%0d  expected=%0d  @%0t ns",
                         label, got, expected, $time);
                fail_count = fail_count + 1;
            end else begin
                $display("pass  %-20s  = %0d", label, got);
            end
        end
    endtask

    // -------------------------------------------------------------------------
    // Main test sequence
    // -------------------------------------------------------------------------
    initial begin
        $dumpfile("sim/seq_test.vcd");
        $dumpvars(0, pulse_sequencer_avalon_tb);

        fail_count    = 0;
        avs_write     = 0;
        avs_read      = 0;
        avs_address   = 0;
        avs_writedata = 0;

        // --- Reset ---
        reset_n = 0;
        repeat (5) @(posedge clk);
        reset_n = 1;
        repeat (2) @(posedge clk);

        // =====================================================================
        // 1. Write all parameters
        // =====================================================================
        $display("\n[1] Writing parameters");
        write_reg(5'h01, 32'd100);  // seq_limit  = 100 cycles (2 us @ 50 MHz)
        write_reg(5'h02, 32'd10);   // rp_start   = 10
        write_reg(5'h03, 32'd20);   // rp_dur     = 20  -> RP active 10..29
        write_reg(5'h04, 32'd40);   // ro_start   = 40
        write_reg(5'h05, 32'd15);   // ro_dur     = 15  -> RO active 40..54
        write_reg(5'h06, 32'd30);   // sync_start = 30  -> SYNC low 30..49 (fixed 20 cycles)
        write_reg(5'h07, 32'd0);    // repeat_limit = 0 (infinite)

        // =====================================================================
        // 2. Read back all parameters
        // =====================================================================
        $display("\n[2] Readback verification");
        read_reg(5'h01); check("seq_limit",    avs_readdata, 32'd100);
        read_reg(5'h02); check("rp_start",     avs_readdata, 32'd10);
        read_reg(5'h03); check("rp_dur",       avs_readdata, 32'd20);
        read_reg(5'h04); check("ro_start",     avs_readdata, 32'd40);
        read_reg(5'h05); check("ro_dur",       avs_readdata, 32'd15);
        read_reg(5'h06); check("sync_start",   avs_readdata, 32'd30);
        read_reg(5'h07); check("repeat_limit", avs_readdata, 32'd0);

        // =====================================================================
        // 3. Verify idle status
        // =====================================================================
        $display("\n[3] Status register (idle)");
        read_reg(5'h00); check("running (idle)",  avs_readdata[0], 1'b0);

        // =====================================================================
        // 4. Start (infinite loop) and verify running
        // =====================================================================
        $display("\n[4] Start sequencer (infinite)");
        write_reg(5'h00, 32'd1);    // bit 0 = start
        // start_trigger is a one-cycle strobe; engine sees it on the cycle after
        // the write register, so allow 3 cycles for the running flag to appear.
        repeat (3) @(posedge clk);
        read_reg(5'h00); check("running (active)", avs_readdata[0], 1'b1);

        // =====================================================================
        // 5. Let it run for ~5 full periods (5 * 100 cycles = 500 clocks)
        //    and visually inspect the VCD for correct pulse shapes.
        // =====================================================================
        $display("\n[5] Running for 5 periods...");
        repeat (500) @(posedge clk);

        // =====================================================================
        // 6. Stop (immediate halt)
        // =====================================================================
        $display("\n[6] Stop sequencer");
        write_reg(5'h00, 32'd2);    // bit 1 = stop
        repeat (3) @(posedge clk);
        read_reg(5'h00); check("running (stopped)", avs_readdata[0], 1'b0);

        // Verify all outputs are in their idle states after stop
        @(negedge clk);
        if (aom_rp_out !== 1'b0) begin
            $display("FAIL  aom_rp_out after stop  = %b  expected 0", aom_rp_out);
            fail_count = fail_count + 1;
        end else
            $display("pass  aom_rp_out after stop  = 0");

        if (aom_ro_out !== 1'b0) begin
            $display("FAIL  aom_ro_out after stop  = %b  expected 0", aom_ro_out);
            fail_count = fail_count + 1;
        end else
            $display("pass  aom_ro_out after stop  = 0");

        if (sync_out !== 1'b1) begin
            $display("FAIL  sync_out after stop    = %b  expected 1 (active-low idle)", sync_out);
            fail_count = fail_count + 1;
        end else
            $display("pass  sync_out after stop    = 1 (idle)");

        // =====================================================================
        // 7. Finite repetition: repeat_limit = 3
        //    Expected: 3 periods execute, then sequencer halts on its own.
        //    repeat_count after completion = 2
        //      (increments on each period boundary; starts at 0, so
        //       0->1 after period 1, 1->2 after period 2, then stops at period 3)
        // =====================================================================
        $display("\n[7] Finite repetitions (3x)");
        write_reg(5'h07, 32'd3);    // repeat_limit = 3
        write_reg(5'h00, 32'd1);    // start

        // Wait well past 3 periods (3 * 100 + margin = 350 cycles)
        repeat (350) @(posedge clk);

        read_reg(5'h00); check("running (finished)",  avs_readdata[0], 1'b0);
        read_reg(5'h08); check("repeat_count",        avs_readdata,    32'd2);

        // =====================================================================
        // Summary
        // =====================================================================
        $display("\n--- Simulation complete: %0d failure(s) ---\n", fail_count);
        if (fail_count == 0)
            $display("ALL TESTS PASSED");
        else
            $display("SOME TESTS FAILED");

        #100;
        $finish;
    end

endmodule

sim/seq_test.vcd
$date
	Tue Feb 24 17:55:17 2026
$end
$version
	Icarus Verilog
$end
$timescale
	1ps
$end
$scope module pulse_sequencer_avalon_tb $end
$var wire 1 ! sync_out $end
$var wire 32 " avs_readdata [31:0] $end
$var wire 1 # aom_rp_out $end
$var wire 1 $ aom_ro_out $end
$var reg 5 % avs_address [4:0] $end
$var reg 1 & avs_read $end
$var reg 1 ' avs_write $end
$var reg 32 ( avs_writedata [31:0] $end
$var reg 1 ) clk $end
$var reg 1 * reset_n $end
$var integer 32 + fail_count [31:0] $end
$scope module uut $end
$var wire 5 , avs_s0_address [4:0] $end
$var wire 1 & avs_s0_read $end
$var wire 1 ' avs_s0_write $end
$var wire 32 - avs_s0_writedata [31:0] $end
$var wire 1 ) clk $end
$var wire 1 * reset_n $end
$var parameter 32 . SYNC_DUR_FIXED $end
$var reg 1 $ aom_ro_out $end
$var reg 1 # aom_rp_out $end
$var reg 32 / avs_s0_readdata [31:0] $end
$var reg 32 0 repeat_count [31:0] $end
$var reg 32 1 repeat_limit [31:0] $end
$var reg 32 2 ro_dur [31:0] $end
$var reg 32 3 ro_start [31:0] $end
$var reg 32 4 rp_dur [31:0] $end
$var reg 32 5 rp_start [31:0] $end
$var reg 1 6 running $end
$var reg 32 7 seq_limit [31:0] $end
$var reg 1 8 start_trigger $end
$var reg 1 9 stop_req $end
$var reg 1 ! sync_out $end
$var reg 32 : sync_start [31:0] $end
$var reg 32 ; timer [31:0] $end
$upscope $end
$scope task check $end
$var reg 32 < expected [31:0] $end
$var reg 32 = got [31:0] $end
$var reg 256 > label [255:0] $end
$upscope $end
$scope task read_reg $end
$var reg 5 ? addr [4:0] $end
$upscope $end
$scope task write_reg $end
$var reg 5 @ addr [4:0] $end
$var reg 32 A data [31:0] $end
$upscope $end
$upscope $end
$enddefinitions $end
$comment Show the parameter values. $end
$dumpall
b10100 .
$end
#0
$dumpvars
bx A
bx @
bx ?
bx >
bx =
bx <
b0 ;
b0 :
09
08
b1001110001000 7
06
b0 5
b0 4
b0 3
b0 2
b1 1
b0 0
b0 /
b0 -
b0 ,
b0 +
0*
0)
b0 (
0'
0&
b0 %
0$
0#
b0 "
1!
$end
#10000
1)
#20000
0)
#30000
1)
#40000
0)
#50000
1)
#60000
0)
#70000
1)
#80000
0)
#90000
1*
1)
#100000
0)
#110000
1)
#120000
0)
#130000
b1100100 A
b1 @
1)
#140000
1'
b1100100 (
b1100100 -
b1 %
b1 ,
0)
#150000
b1100100 7
1)
#160000
b1010 A
b10 @
0'
0)
#170000
1)
#180000
1'
b1010 (
b1010 -
b10 %
b10 ,
0)
#190000
b1010 5
1)
#200000
b10100 A
b11 @
0'
0)
#210000
1)
#220000
1'
b10100 (
b10100 -
b11 %
b11 ,
0)
#230000
b10100 4
1)
#240000
b101000 A
b100 @
0'
0)
#250000
1)
#260000
1'
b101000 (
b101000 -
b100 %
b100 ,
0)
#270000
b101000 3
1)
#280000
b1111 A
b101 @
0'
0)
#290000
1)
#300000
1'
b1111 (
b1111 -
b101 %
b101 ,
0)
#310000
b1111 2
1)
#320000
b11110 A
b110 @
0'
0)
#330000
1)
#340000
1'
b11110 (
b11110 -
b110 %
b110 ,
0)
#350000
b11110 :
1)
#360000
b0 A
b111 @
0'
0)
#370000
1)
#380000
1'
b0 (
b0 -
b111 %
b111 ,
0)
#390000
b0 1
1)
#400000
b1 ?
0'
0)
#410000
1)
#420000
1&
b1 %
b1 ,
0)
#430000
b1100100 "
b1100100 /
1)
#440000
b10 ?
b1100100 <
b1100100 =
b11100110110010101110001010111110110110001101001011011010110100101110100 >
0&
0)
#450000
1)
#460000
1&
b10 %
b10 ,
0)
#470000
b1010 "
b1010 /
1)
#480000
b11 ?
b1010 <
b1010 =
b111001001110000010111110111001101110100011000010111001001110100 >
0&
0)
#490000
1)
#500000
1&
b11 %
b11 ,
0)
#510000
b10100 "
b10100 /
1)
#520000
b100 ?
b10100 <
b10100 =
b11100100111000001011111011001000111010101110010 >
0&
0)
#530000
1)
#540000
1&
b100 %
b100 ,
0)
#550000
b101000 "
b101000 /
1)
#560000
b101 ?
b101000 <
b101000 =
b111001001101111010111110111001101110100011000010111001001110100 >
0&
0)
#570000
1)
#580000
1&
b101 %
b101 ,
0)
#590000
b1111 "
b1111 /
1)
#600000
b110 ?
b1111 <
b1111 =
b11100100110111101011111011001000111010101110010 >
0&
0)
#610000
1)
#620000
1&
b110 %
b110 ,
0)
#630000
b11110 "
b11110 /
1)
#640000
b111 ?
b11110 <
b11110 =
b1110011011110010110111001100011010111110111001101110100011000010111001001110100 >
0&
0)
#650000
1)
#660000
1&
b111 %
b111 ,
0)
#670000
b0 "
b0 /
1)
#680000
b0 ?
b0 <
b0 =
b11100100110010101110000011001010110000101110100010111110110110001101001011011010110100101110100 >
0&
0)
#690000
1)
#700000
1&
b0 %
b0 ,
0)
#710000
1)
#720000
b1 A
b0 @
b111001001110101011011100110111001101001011011100110011100100000001010000110100101100100011011000110010100101001 >
0&
0)
#730000
1)
#740000
1'
b1 (
b1 -
0)
#750000
18
1)
#760000
0'
0)
#770000
16
08
1)
#780000
0)
#790000
b1 ;
1)
#800000
0)
#810000
b10 ;
1)
#820000
1&
0)
#830000
b1 "
b1 /
b11 ;
1)
#840000
b1 <
b1 =
b1110010011101010110111001101110011010010110111001100111001000000010100001100001011000110111010001101001011101100110010100101001 >
0&
0)
#850000
b100 ;
1)
#860000
0)
#870000
b101 ;
1)
#880000
0)
#890000
b110 ;
1)
#900000
0)
#910000
b111 ;
1)
#920000
0)
#930000
b1000 ;
1)
#940000
0)
#950000
b1001 ;
1)
#960000
0)
#970000
b1010 ;
1)
#980000
0)
#990000
1#
b1011 ;
1)
#1000000
0)
#1010000
b1100 ;
1)
#1020000
0)
#1030000
b1101 ;
1)
#1040000
0)
#1050000
b1110 ;
1)
#1060000
0)
#1070000
b1111 ;
1)
#1080000
0)
#1090000
b10000 ;
1)
#1100000
0)
#1110000
b10001 ;
1)
#1120000
0)
#1130000
b10010 ;
1)
#1140000
0)
#1150000
b10011 ;
1)
#1160000
0)
#1170000
b10100 ;
1)
#1180000
0)
#1190000
b10101 ;
1)
#1200000
0)
#1210000
b10110 ;
1)
#1220000
0)
#1230000
b10111 ;
1)
#1240000
0)
#1250000
b11000 ;
1)
#1260000
0)
#1270000
b11001 ;
1)
#1280000
0)
#1290000
b11010 ;
1)
#1300000
0)
#1310000
b11011 ;
1)
#1320000
0)
#1330000
b11100 ;
1)
#1340000
0)
#1350000
b11101 ;
1)
#1360000
0)
#1370000
b11110 ;
1)
#1380000
0)
#1390000
0!
0#
b11111 ;
1)
#1400000
0)
#1410000
b100000 ;
1)
#1420000
0)
#1430000
b100001 ;
1)
#1440000
0)
#1450000
b100010 ;
1)
#1460000
0)
#1470000
b100011 ;
1)
#1480000
0)
#1490000
b100100 ;
1)
#1500000
0)
#1510000
b100101 ;
1)
#1520000
0)
#1530000
b100110 ;
1)
#1540000
0)
#1550000
b100111 ;
1)
#1560000
0)
#1570000
b101000 ;
1)
#1580000
0)
#1590000
1$
b101001 ;
1)
#1600000
0)
#1610000
b101010 ;
1)
#1620000
0)
#1630000
b101011 ;
1)
#1640000
0)
#1650000
b101100 ;
1)
#1660000
0)
#1670000
b101101 ;
1)
#1680000
0)
#1690000
b101110 ;
1)
#1700000
0)
#1710000
b101111 ;
1)
#1720000
0)
#1730000
b110000 ;
1)
#1740000
0)
#1750000
b110001 ;
1)
#1760000
0)
#1770000
b110010 ;
1)
#1780000
0)
#1790000
1!
b110011 ;
1)
#1800000
0)
#1810000
b110100 ;
1)
#1820000
0)
#1830000
b110101 ;
1)
#1840000
0)
#1850000
b110110 ;
1)
#1860000
0)
#1870000
b110111 ;
1)
#1880000
0)
#1890000
0$
b111000 ;
1)
#1900000
0)
#1910000
b111001 ;
1)
#1920000
0)
#1930000
b111010 ;
1)
#1940000
0)
#1950000
b111011 ;
1)
#1960000
0)
#1970000
b111100 ;
1)
#1980000
0)
#1990000
b111101 ;
1)
#2000000
0)
#2010000
b111110 ;
1)
#2020000
0)
#2030000
b111111 ;
1)
#2040000
0)
#2050000
b1000000 ;
1)
#2060000
0)
#2070000
b1000001 ;
1)
#2080000
0)
#2090000
b1000010 ;
1)
#2100000
0)
#2110000
b1000011 ;
1)
#2120000
0)
#2130000
b1000100 ;
1)
#2140000
0)
#2150000
b1000101 ;
1)
#2160000
0)
#2170000
b1000110 ;
1)
#2180000
0)
#2190000
b1000111 ;
1)
#2200000
0)
#2210000
b1001000 ;
1)
#2220000
0)
#2230000
b1001001 ;
1)
#2240000
0)
#2250000
b1001010 ;
1)
#2260000
0)
#2270000
b1001011 ;
1)
#2280000
0)
#2290000
b1001100 ;
1)
#2300000
0)
#2310000
b1001101 ;
1)
#2320000
0)
#2330000
b1001110 ;
1)
#2340000
0)
#2350000
b1001111 ;
1)
#2360000
0)
#2370000
b1010000 ;
1)
#2380000
0)
#2390000
b1010001 ;
1)
#2400000
0)
#2410000
b1010010 ;
1)
#2420000
0)
#2430000
b1010011 ;
1)
#2440000
0)
#2450000
b1010100 ;
1)
#2460000
0)
#2470000
b1010101 ;
1)
#2480000
0)
#2490000
b1010110 ;
1)
#2500000
0)
#2510000
b1010111 ;
1)
#2520000
0)
#2530000
b1011000 ;
1)
#2540000
0)
#2550000
b1011001 ;
1)
#2560000
0)
#2570000
b1011010 ;
1)
#2580000
0)
#2590000
b1011011 ;
1)
#2600000
0)
#2610000
b1011100 ;
1)
#2620000
0)
#2630000
b1011101 ;
1)
#2640000
0)
#2650000
b1011110 ;
1)
#2660000
0)
#2670000
b1011111 ;
1)
#2680000
0)
#2690000
b1100000 ;
1)
#2700000
0)
#2710000
b1100001 ;
1)
#2720000
0)
#2730000
b1100010 ;
1)
#2740000
0)
#2750000
b1100011 ;
1)
#2760000
0)
#2770000
b1 0
b0 ;
1)
#2780000
0)
#2790000
b1 ;
1)
#2800000
0)
#2810000
b10 ;
1)
#2820000
0)
#2830000
b11 ;
1)
#2840000
0)
#2850000
b100 ;
1)
#2860000
0)
#2870000
b101 ;
1)
#2880000
0)
#2890000
b110 ;
1)
#2900000
0)
#2910000
b111 ;
1)
#2920000
0)
#2930000
b1000 ;
1)
#2940000
0)
#2950000
b1001 ;
1)
#2960000
0)
#2970000
b1010 ;
1)
#2980000
0)
#2990000
1#
b1011 ;
1)
#3000000
0)
#3010000
b1100 ;
1)
#3020000
0)
#3030000
b1101 ;
1)
#3040000
0)
#3050000
b1110 ;
1)
#3060000
0)
#3070000
b1111 ;
1)
#3080000
0)
#3090000
b10000 ;
1)
#3100000
0)
#3110000
b10001 ;
1)
#3120000
0)
#3130000
b10010 ;
1)
#3140000
0)
#3150000
b10011 ;
1)
#3160000
0)
#3170000
b10100 ;
1)
#3180000
0)
#3190000
b10101 ;
1)
#3200000
0)
#3210000
b10110 ;
1)
#3220000
0)
#3230000
b10111 ;
1)
#3240000
0)
#3250000
b11000 ;
1)
#3260000
0)
#3270000
b11001 ;
1)
#3280000
0)
#3290000
b11010 ;
1)
#3300000
0)
#3310000
b11011 ;
1)
#3320000
0)
#3330000
b11100 ;
1)
#3340000
0)
#3350000
b11101 ;
1)
#3360000
0)
#3370000
b11110 ;
1)
#3380000
0)
#3390000
0!
0#
b11111 ;
1)
#3400000
0)
#3410000
b100000 ;
1)
#3420000
0)
#3430000
b100001 ;
1)
#3440000
0)
#3450000
b100010 ;
1)
#3460000
0)
#3470000
b100011 ;
1)
#3480000
0)
#3490000
b100100 ;
1)
#3500000
0)
#3510000
b100101 ;
1)
#3520000
0)
#3530000
b100110 ;
1)
#3540000
0)
#3550000
b100111 ;
1)
#3560000
0)
#3570000
b101000 ;
1)
#3580000
0)
#3590000
1$
b101001 ;
1)
#3600000
0)
#3610000
b101010 ;
1)
#3620000
0)
#3630000
b101011 ;
1)
#3640000
0)
#3650000
b101100 ;
1)
#3660000
0)
#3670000
b101101 ;
1)
#3680000
0)
#3690000
b101110 ;
1)
#3700000
0)
#3710000
b101111 ;
1)
#3720000
0)
#3730000
b110000 ;
1)
#3740000
0)
#3750000
b110001 ;
1)
#3760000
0)
#3770000
b110010 ;
1)
#3780000
0)
#3790000
1!
b110011 ;
1)
#3800000
0)
#3810000
b110100 ;
1)
#3820000
0)
#3830000
b110101 ;
1)
#3840000
0)
#3850000
b110110 ;
1)
#3860000
0)
#3870000
b110111 ;
1)
#3880000
0)
#3890000
0$
b111000 ;
1)
#3900000
0)
#3910000
b111001 ;
1)
#3920000
0)
#3930000
b111010 ;
1)
#3940000
0)
#3950000
b111011 ;
1)
#3960000
0)
#3970000
b111100 ;
1)
#3980000
0)
#3990000
b111101 ;
1)
#4000000
0)
#4010000
b111110 ;
1)
#4020000
0)
#4030000
b111111 ;
1)
#4040000
0)
#4050000
b1000000 ;
1)
#4060000
0)
#4070000
b1000001 ;
1)
#4080000
0)
#4090000
b1000010 ;
1)
#4100000
0)
#4110000
b1000011 ;
1)
#4120000
0)
#4130000
b1000100 ;
1)
#4140000
0)
#4150000
b1000101 ;
1)
#4160000
0)
#4170000
b1000110 ;
1)
#4180000
0)
#4190000
b1000111 ;
1)
#4200000
0)
#4210000
b1001000 ;
1)
#4220000
0)
#4230000
b1001001 ;
1)
#4240000
0)
#4250000
b1001010 ;
1)
#4260000
0)
#4270000
b1001011 ;
1)
#4280000
0)
#4290000
b1001100 ;
1)
#4300000
0)
#4310000
b1001101 ;
1)
#4320000
0)
#4330000
b1001110 ;
1)
#4340000
0)
#4350000
b1001111 ;
1)
#4360000
0)
#4370000
b1010000 ;
1)
#4380000
0)
#4390000
b1010001 ;
1)
#4400000
0)
#4410000
b1010010 ;
1)
#4420000
0)
#4430000
b1010011 ;
1)
#4440000
0)
#4450000
b1010100 ;
1)
#4460000
0)
#4470000
b1010101 ;
1)
#4480000
0)
#4490000
b1010110 ;
1)
#4500000
0)
#4510000
b1010111 ;
1)
#4520000
0)
#4530000
b1011000 ;
1)
#4540000
0)
#4550000
b1011001 ;
1)
#4560000
0)
#4570000
b1011010 ;
1)
#4580000
0)
#4590000
b1011011 ;
1)
#4600000
0)
#4610000
b1011100 ;
1)
#4620000
0)
#4630000
b1011101 ;
1)
#4640000
0)
#4650000
b1011110 ;
1)
#4660000
0)
#4670000
b1011111 ;
1)
#4680000
0)
#4690000
b1100000 ;
1)
#4700000
0)
#4710000
b1100001 ;
1)
#4720000
0)
#4730000
b1100010 ;
1)
#4740000
0)
#4750000
b1100011 ;
1)
#4760000
0)
#4770000
b10 0
b0 ;
1)
#4780000
0)
#4790000
b1 ;
1)
#4800000
0)
#4810000
b10 ;
1)
#4820000
0)
#4830000
b11 ;
1)
#4840000
0)
#4850000
b100 ;
1)
#4860000
0)
#4870000
b101 ;
1)
#4880000
0)
#4890000
b110 ;
1)
#4900000
0)
#4910000
b111 ;
1)
#4920000
0)
#4930000
b1000 ;
1)
#4940000
0)
#4950000
b1001 ;
1)
#4960000
0)
#4970000
b1010 ;
1)
#4980000
0)
#4990000
1#
b1011 ;
1)
#5000000
0)
#5010000
b1100 ;
1)
#5020000
0)
#5030000
b1101 ;
1)
#5040000
0)
#5050000
b1110 ;
1)
#5060000
0)
#5070000
b1111 ;
1)
#5080000
0)
#5090000
b10000 ;
1)
#5100000
0)
#5110000
b10001 ;
1)
#5120000
0)
#5130000
b10010 ;
1)
#5140000
0)
#5150000
b10011 ;
1)
#5160000
0)
#5170000
b10100 ;
1)
#5180000
0)
#5190000
b10101 ;
1)
#5200000
0)
#5210000
b10110 ;
1)
#5220000
0)
#5230000
b10111 ;
1)
#5240000
0)
#5250000
b11000 ;
1)
#5260000
0)
#5270000
b11001 ;
1)
#5280000
0)
#5290000
b11010 ;
1)
#5300000
0)
#5310000
b11011 ;
1)
#5320000
0)
#5330000
b11100 ;
1)
#5340000
0)
#5350000
b11101 ;
1)
#5360000
0)
#5370000
b11110 ;
1)
#5380000
0)
#5390000
0!
0#
b11111 ;
1)
#5400000
0)
#5410000
b100000 ;
1)
#5420000
0)
#5430000
b100001 ;
1)
#5440000
0)
#5450000
b100010 ;
1)
#5460000
0)
#5470000
b100011 ;
1)
#5480000
0)
#5490000
b100100 ;
1)
#5500000
0)
#5510000
b100101 ;
1)
#5520000
0)
#5530000
b100110 ;
1)
#5540000
0)
#5550000
b100111 ;
1)
#5560000
0)
#5570000
b101000 ;
1)
#5580000
0)
#5590000
1$
b101001 ;
1)
#5600000
0)
#5610000
b101010 ;
1)
#5620000
0)
#5630000
b101011 ;
1)
#5640000
0)
#5650000
b101100 ;
1)
#5660000
0)
#5670000
b101101 ;
1)
#5680000
0)
#5690000
b101110 ;
1)
#5700000
0)
#5710000
b101111 ;
1)
#5720000
0)
#5730000
b110000 ;
1)
#5740000
0)
#5750000
b110001 ;
1)
#5760000
0)
#5770000
b110010 ;
1)
#5780000
0)
#5790000
1!
b110011 ;
1)
#5800000
0)
#5810000
b110100 ;
1)
#5820000
0)
#5830000
b110101 ;
1)
#5840000
0)
#5850000
b110110 ;
1)
#5860000
0)
#5870000
b110111 ;
1)
#5880000
0)
#5890000
0$
b111000 ;
1)
#5900000
0)
#5910000
b111001 ;
1)
#5920000
0)
#5930000
b111010 ;
1)
#5940000
0)
#5950000
b111011 ;
1)
#5960000
0)
#5970000
b111100 ;
1)
#5980000
0)
#5990000
b111101 ;
1)
#6000000
0)
#6010000
b111110 ;
1)
#6020000
0)
#6030000
b111111 ;
1)
#6040000
0)
#6050000
b1000000 ;
1)
#6060000
0)
#6070000
b1000001 ;
1)
#6080000
0)
#6090000
b1000010 ;
1)
#6100000
0)
#6110000
b1000011 ;
1)
#6120000
0)
#6130000
b1000100 ;
1)
#6140000
0)
#6150000
b1000101 ;
1)
#6160000
0)
#6170000
b1000110 ;
1)
#6180000
0)
#6190000
b1000111 ;
1)
#6200000
0)
#6210000
b1001000 ;
1)
#6220000
0)
#6230000
b1001001 ;
1)
#6240000
0)
#6250000
b1001010 ;
1)
#6260000
0)
#6270000
b1001011 ;
1)
#6280000
0)
#6290000
b1001100 ;
1)
#6300000
0)
#6310000
b1001101 ;
1)
#6320000
0)
#6330000
b1001110 ;
1)
#6340000
0)
#6350000
b1001111 ;
1)
#6360000
0)
#6370000
b1010000 ;
1)
#6380000
0)
#6390000
b1010001 ;
1)
#6400000
0)
#6410000
b1010010 ;
1)
#6420000
0)
#6430000
b1010011 ;
1)
